Dhan_Tradehull/Dhan_Tradehull.py
Dhan_Tradehull/__init__.py
dhan_tradehull-3.2.0.dist-info/METADATA
dhan_tradehull-3.2.0.dist-info/WHEEL
dhan_tradehull-3.2.0.dist-info/top_level.txt
dhan_tradehull-3.2.0.dist-info/RECORD
