Metadata-Version: 2.4
Name: Dhan_Tradehull
Version: 3.2.0
Summary: A Dhan Codebase from TradeHull
Home-page: https://github.com/TradeHull/Dhan_Tradehull
Author: TradeHull
Author-email: contact.tradehull@gmail.com
Classifier: Programming Language :: Python :: 3
Classifier: License :: OSI Approved :: MIT License
Classifier: Operating System :: OS Independent
Requires-Python: >=3.10
Requires-Dist: dhanhq>=2.1.0
Requires-Dist: mibian>=0.1.3
Requires-Dist: numpy>=1.24.4
Requires-Dist: pandas>=2.0.3
Requires-Dist: pytz>=2024.1
Requires-Dist: requests>=2.32.3
Requires-Dist: websocket-client>=1.8.0
Dynamic: author
Dynamic: author-email
Dynamic: classifier
Dynamic: description
Dynamic: description-content-type
Dynamic: home-page
Dynamic: requires-dist
Dynamic: requires-python
Dynamic: summary
